LICENSE
MANIFEST.in
README.md
requirements.txt
setup.cfg
setup.py
animesr/__init__.py
animesr/anime_videos_preprocessing.py
animesr/demo.py
animesr/inference_animesr_frames.py
animesr/inference_animesr_video.py
animesr/test.py
animesr/train.py
animesr.egg-info/PKG-INFO
animesr.egg-info/SOURCES.txt
animesr.egg-info/dependency_links.txt
animesr.egg-info/requires.txt
animesr.egg-info/top_level.txt
animesr/archs/__init__.py
animesr/archs/discriminator_arch.py
animesr/archs/simple_degradation_arch.py
animesr/archs/vsr_arch.py
animesr/data/__init__.py
animesr/data/data_utils.py
animesr/data/ffmpeg_anime_dataset.py
animesr/data/ffmpeg_anime_lbo_dataset.py
animesr/data/paired_image_dataset.py
animesr/models/__init__.py
animesr/models/degradation_gan_model.py
animesr/models/degradation_model.py
animesr/models/video_recurrent_gan_model.py
animesr/models/video_recurrent_model.py
animesr/utils/__init__.py
animesr/utils/inference_base.py
animesr/utils/shot_detector.py
animesr/utils/video_util.py